[
    {
        "Category":  "Cumulative",
        "KBNumber":  "4464217",
        "KBTitle":  "2018-09 Cumulative Update for Windows 10 Version 1709 for x86-based Systems (KB4464217)",
        "KBUrl":  "http://support.microsoft.com/help/4464217",
        "Severity":  "",
        "DatePosted":  "\/Date(1537203605000)\/",
        "DateRevised":  "\/Date(1537203605000)\/",
        "DateCreated":  "\/Date(1537206019000)\/",
        "DateLastModified":  "\/Date(1537206019000)\/",
        "FileName":  "Windows10.0-KB4464217-x86.cab",
        "URL":  "http://download.windowsupdate.com/d/msdownload/update/software/updt/2018/09/windows10.0-kb4464217-x86_e0b54bb0a2deaced403825b116793d4ce2d65457.cab"
    },
    {
        "Category":  "Cumulative",
        "KBNumber":  "4464217",
        "KBTitle":  "2018-09 Cumulative Update for Windows Server 2016 (1709) for x64-based Systems (KB4464217)",
        "KBUrl":  "http://support.microsoft.com/help/4464217",
        "Severity":  "",
        "DatePosted":  "\/Date(1537203605000)\/",
        "DateRevised":  "\/Date(1537203605000)\/",
        "DateCreated":  "\/Date(1537206027000)\/",
        "DateLastModified":  "\/Date(1537206027000)\/",
        "FileName":  "Windows10.0-KB4464217-x64.cab",
        "URL":  "http://download.windowsupdate.com/c/msdownload/update/software/updt/2018/09/windows10.0-kb4464217-x64_e8164fa36ed5cd1d59430cdbff0071cc229a49c2.cab"
    },
    {
        "Category":  "Cumulative",
        "KBNumber":  "4464217",
        "KBTitle":  "2018-09 Cumulative Update for Windows 10 Version 1709 for x64-based Systems (KB4464217)",
        "KBUrl":  "http://support.microsoft.com/help/4464217",
        "Severity":  "",
        "DatePosted":  "\/Date(1537203605000)\/",
        "DateRevised":  "\/Date(1537203605000)\/",
        "DateCreated":  "\/Date(1537206024000)\/",
        "DateLastModified":  "\/Date(1537206024000)\/",
        "FileName":  "Windows10.0-KB4464217-x64.cab",
        "URL":  "http://download.windowsupdate.com/c/msdownload/update/software/updt/2018/09/windows10.0-kb4464217-x64_e8164fa36ed5cd1d59430cdbff0071cc229a49c2.cab"
    },
    {
        "Category":  "Cumulative",
        "KBNumber":  "4464218",
        "KBTitle":  "2018-09 Cumulative Update for Windows Server 2016 (1803) for x64-based Systems (KB4464218)",
        "KBUrl":  "http://support.microsoft.com/help/4464218",
        "Severity":  "",
        "DatePosted":  "\/Date(1537203605000)\/",
        "DateRevised":  "\/Date(1537203605000)\/",
        "DateCreated":  "\/Date(1537206026000)\/",
        "DateLastModified":  "\/Date(1537206026000)\/",
        "FileName":  "Windows10.0-KB4464218-x64.cab",
        "URL":  "http://download.windowsupdate.com/d/msdownload/update/software/updt/2018/09/windows10.0-kb4464218-x64_d7cd7f9a6bb895cc638634339dec8a5a47a10b3d.cab"
    },
    {
        "Category":  "Cumulative",
        "KBNumber":  "4464218",
        "KBTitle":  "2018-09 Cumulative Update for Windows 10 Version 1803 for x86-based Systems (KB4464218)",
        "KBUrl":  "http://support.microsoft.com/help/4464218",
        "Severity":  "",
        "DatePosted":  "\/Date(1537203605000)\/",
        "DateRevised":  "\/Date(1537203605000)\/",
        "DateCreated":  "\/Date(1537206028000)\/",
        "DateLastModified":  "\/Date(1537206028000)\/",
        "FileName":  "Windows10.0-KB4464218-x86.cab",
        "URL":  "http://download.windowsupdate.com/d/msdownload/update/software/updt/2018/09/windows10.0-kb4464218-x86_08a9bc783e809466c7f02c78a6fd74cba5c6632b.cab"
    },
    {
        "Category":  "Cumulative",
        "KBNumber":  "4464218",
        "KBTitle":  "2018-09 Cumulative Update for Windows 10 Version 1803 for x64-based Systems (KB4464218)",
        "KBUrl":  "http://support.microsoft.com/help/4464218",
        "Severity":  "",
        "DatePosted":  "\/Date(1537203605000)\/",
        "DateRevised":  "\/Date(1537203605000)\/",
        "DateCreated":  "\/Date(1537206028000)\/",
        "DateLastModified":  "\/Date(1537206028000)\/",
        "FileName":  "Windows10.0-KB4464218-x64.cab",
        "URL":  "http://download.windowsupdate.com/d/msdownload/update/software/updt/2018/09/windows10.0-kb4464218-x64_d7cd7f9a6bb895cc638634339dec8a5a47a10b3d.cab"
    },
    {
        "Category":  "Servicing",
        "KBNumber":  "4456655",
        "KBTitle":  "2018-09 Update for Windows 10 Version 1803 for x64-based Systems (KB4456655)",
        "KBUrl":  "http://support.microsoft.com/help/4456655",
        "Severity":  "",
        "DatePosted":  "\/Date(1536685205000)\/",
        "DateRevised":  "\/Date(1536789600000)\/",
        "DateCreated":  "\/Date(1536688325000)\/",
        "DateLastModified":  "\/Date(1536860252000)\/",
        "FileName":  "Windows10.0-KB4456655-x64.cab",
        "URL":  "http://download.windowsupdate.com/d/msdownload/update/software/crup/2018/09/windows10.0-kb4456655-x64_5e43ed4e6b018b0dba477a2493227401c42533f4.cab"
    },
    {
        "Category":  "Servicing",
        "KBNumber":  "4456655",
        "KBTitle":  "2018-09 Update for Windows 10 Version 1803 for x86-based Systems (KB4456655)",
        "KBUrl":  "http://support.microsoft.com/help/4456655",
        "Severity":  "",
        "DatePosted":  "\/Date(1536685205000)\/",
        "DateRevised":  "\/Date(1536789600000)\/",
        "DateCreated":  "\/Date(1536688324000)\/",
        "DateLastModified":  "\/Date(1536860253000)\/",
        "FileName":  "Windows10.0-KB4456655-x86.cab",
        "URL":  "http://download.windowsupdate.com/c/msdownload/update/software/crup/2018/09/windows10.0-kb4456655-x86_f5d98db06899c8f6817656f6f57ea59dc282b559.cab"
    },
    {
        "Category":  "Servicing",
        "KBNumber":  "4456655",
        "KBTitle":  "2018-09 Update for Windows Server 2016 (1803) for x64-based Systems (KB4456655)",
        "KBUrl":  "http://support.microsoft.com/help/4456655",
        "Severity":  "",
        "DatePosted":  "\/Date(1536685205000)\/",
        "DateRevised":  "\/Date(1536789600000)\/",
        "DateCreated":  "\/Date(1536688318000)\/",
        "DateLastModified":  "\/Date(1536860255000)\/",
        "FileName":  "Windows10.0-KB4456655-x64.cab",
        "URL":  "http://download.windowsupdate.com/d/msdownload/update/software/crup/2018/09/windows10.0-kb4456655-x64_5e43ed4e6b018b0dba477a2493227401c42533f4.cab"
    },
    {
        "Category":  "Adobe",
        "KBNumber":  "4457146",
        "KBTitle":  "2018-09 Security Update for Adobe Flash Player for Windows 10 Version 1709 for x64-based Systems (KB4457146)",
        "KBUrl":  "http://support.microsoft.com/help/4457146",
        "Severity":  "Critical",
        "DatePosted":  "\/Date(1536685210000)\/",
        "DateRevised":  "\/Date(1536685210000)\/",
        "DateCreated":  "\/Date(1536688339000)\/",
        "DateLastModified":  "\/Date(1536688339000)\/",
        "FileName":  "Windows10.0-KB4457146-x64.cab",
        "URL":  "http://download.windowsupdate.com/c/msdownload/update/software/secu/2018/09/windows10.0-kb4457146-x64_ae5ddb6731777fcf1358a62644c3702803c42da5.cab"
    },
    {
        "Category":  "Adobe",
        "KBNumber":  "4457146",
        "KBTitle":  "2018-09 Security Update for Adobe Flash Player for Windows 10 Version 1709 for x86-based Systems (KB4457146)",
        "KBUrl":  "http://support.microsoft.com/help/4457146",
        "Severity":  "Critical",
        "DatePosted":  "\/Date(1536685210000)\/",
        "DateRevised":  "\/Date(1536685210000)\/",
        "DateCreated":  "\/Date(1536688338000)\/",
        "DateLastModified":  "\/Date(1536688338000)\/",
        "FileName":  "Windows10.0-KB4457146-x86.cab",
        "URL":  "http://download.windowsupdate.com/c/msdownload/update/software/secu/2018/09/windows10.0-kb4457146-x86_5c49e5059285d4fa77e3d1bb87a88f67b07943dc.cab"
    },
    {
        "Category":  "Adobe",
        "KBNumber":  "4457146",
        "KBTitle":  "2018-09 Security Update for Adobe Flash Player for Windows 10 Version 1507 for x64-based Systems (KB4457146)",
        "KBUrl":  "http://support.microsoft.com/help/4457146",
        "Severity":  "Critical",
        "DatePosted":  "\/Date(1536685209000)\/",
        "DateRevised":  "\/Date(1536685209000)\/",
        "DateCreated":  "\/Date(1536688343000)\/",
        "DateLastModified":  "\/Date(1536688343000)\/",
        "FileName":  "Windows10.0-KB4457146-X64.cab",
        "URL":  "http://download.windowsupdate.com/d/msdownload/update/software/secu/2018/09/windows10.0-kb4457146-x64_851746c50dbc5bae8d91df818639d1fa0cc176a7.cab"
    },
    {
        "Category":  "Adobe",
        "KBNumber":  "4457146",
        "KBTitle":  "2018-09 Security Update for Adobe Flash Player for Windows 10 Version 1507 for x86-based Systems (KB4457146)",
        "KBUrl":  "http://support.microsoft.com/help/4457146",
        "Severity":  "Critical",
        "DatePosted":  "\/Date(1536685209000)\/",
        "DateRevised":  "\/Date(1536685209000)\/",
        "DateCreated":  "\/Date(1536688349000)\/",
        "DateLastModified":  "\/Date(1536688349000)\/",
        "FileName":  "Windows10.0-KB4457146-X86.cab",
        "URL":  "http://download.windowsupdate.com/c/msdownload/update/software/secu/2018/09/windows10.0-kb4457146-x86_03534027aaaf0c68947ffbbe52ee00e2233c2b4c.cab"
    },
    {
        "Category":  "Adobe",
        "KBNumber":  "4457146",
        "KBTitle":  "2018-09 Security Update for Adobe Flash Player for Windows 10 Version 1803 for x86-based Systems (KB4457146)",
        "KBUrl":  "http://support.microsoft.com/help/4457146",
        "Severity":  "Critical",
        "DatePosted":  "\/Date(1536685207000)\/",
        "DateRevised":  "\/Date(1536685207000)\/",
        "DateCreated":  "\/Date(1536688350000)\/",
        "DateLastModified":  "\/Date(1536688350000)\/",
        "FileName":  "Windows10.0-KB4457146-x86.cab",
        "URL":  "http://download.windowsupdate.com/c/msdownload/update/software/secu/2018/09/windows10.0-kb4457146-x86_9c5a2052144f62659cc5ef0d15f7fc570be77467.cab"
    },
    {
        "Category":  "Adobe",
        "KBNumber":  "4457146",
        "KBTitle":  "2018-09 Security Update for Adobe Flash Player for Windows 10 Version 1803 for x64-based Systems (KB4457146)",
        "KBUrl":  "http://support.microsoft.com/help/4457146",
        "Severity":  "Critical",
        "DatePosted":  "\/Date(1536685207000)\/",
        "DateRevised":  "\/Date(1536685207000)\/",
        "DateCreated":  "\/Date(1536688348000)\/",
        "DateLastModified":  "\/Date(1536688348000)\/",
        "FileName":  "Windows10.0-KB4457146-x64.cab",
        "URL":  "http://download.windowsupdate.com/c/msdownload/update/software/secu/2018/09/windows10.0-kb4457146-x64_1526dfdda17e7593f9e9c483bee80d85c1be97a8.cab"
    },
    {
        "Category":  "Adobe",
        "KBNumber":  "4457146",
        "KBTitle":  "2018-09 Security Update for Adobe Flash Player for Windows 10 Version 1703 for x64-based Systems (KB4457146)",
        "KBUrl":  "http://support.microsoft.com/help/4457146",
        "Severity":  "Critical",
        "DatePosted":  "\/Date(1536685206000)\/",
        "DateRevised":  "\/Date(1536685206000)\/",
        "DateCreated":  "\/Date(1536688337000)\/",
        "DateLastModified":  "\/Date(1536688337000)\/",
        "FileName":  "Windows10.0-KB4457146-X64.cab",
        "URL":  "http://download.windowsupdate.com/c/msdownload/update/software/secu/2018/09/windows10.0-kb4457146-x64_4c4019c123eee140e8cc25b3b79e46e4e3c84164.cab"
    },
    {
        "Category":  "Adobe",
        "KBNumber":  "4457146",
        "KBTitle":  "2018-09 Security Update for Adobe Flash Player for Windows 10 Version 1703 for x86-based Systems (KB4457146)",
        "KBUrl":  "http://support.microsoft.com/help/4457146",
        "Severity":  "Critical",
        "DatePosted":  "\/Date(1536685206000)\/",
        "DateRevised":  "\/Date(1536685206000)\/",
        "DateCreated":  "\/Date(1536688338000)\/",
        "DateLastModified":  "\/Date(1536688338000)\/",
        "FileName":  "Windows10.0-KB4457146-X86.cab",
        "URL":  "http://download.windowsupdate.com/d/msdownload/update/software/secu/2018/09/windows10.0-kb4457146-x86_d8a827fcba7721f08f0de991bebe909d158571b2.cab"
    },
    {
        "Category":  "Cumulative",
        "KBNumber":  "4457131",
        "KBTitle":  "2018-09 Cumulative Update for Windows Server 2016 (1607) for x64-based Systems (KB4457131)",
        "KBUrl":  "http://support.microsoft.com/help/4457131",
        "Severity":  "Critical",
        "DatePosted":  "\/Date(1536685205000)\/",
        "DateRevised":  "\/Date(1536685205000)\/",
        "DateCreated":  "\/Date(1536688241000)\/",
        "DateLastModified":  "\/Date(1536688241000)\/",
        "FileName":  "Windows10.0-KB4457131-x64.cab",
        "URL":  "http://download.windowsupdate.com/d/msdownload/update/software/secu/2018/09/windows10.0-kb4457131-x64_786e1ea5672e25d698548a3a966f48ce16530746.cab"
    },
    {
        "Category":  "Adobe",
        "KBNumber":  "4457146",
        "KBTitle":  "2018-09 Security Update for Adobe Flash Player for Windows Server 2016 (1607) for x64-based Systems (KB4457146)",
        "KBUrl":  "http://support.microsoft.com/help/4457146",
        "Severity":  "Critical",
        "DatePosted":  "\/Date(1536685205000)\/",
        "DateRevised":  "\/Date(1536685205000)\/",
        "DateCreated":  "\/Date(1536688312000)\/",
        "DateLastModified":  "\/Date(1536688312000)\/",
        "FileName":  "Windows10.0-KB4457146-X64.cab",
        "URL":  "http://download.windowsupdate.com/d/msdownload/update/software/secu/2018/09/windows10.0-kb4457146-x64_8a4219fe58dfb1857c68c2d23092721e9bfe2f7a.cab"
    },
    {
        "Category":  "Cumulative",
        "KBNumber":  "4457138",
        "KBTitle":  "2018-09 Cumulative Update for Windows 10 Version 1703 for x86-based Systems (KB4457138)",
        "KBUrl":  "http://support.microsoft.com/help/4457138",
        "Severity":  "Critical",
        "DatePosted":  "\/Date(1536685205000)\/",
        "DateRevised":  "\/Date(1536685205000)\/",
        "DateCreated":  "\/Date(1536688326000)\/",
        "DateLastModified":  "\/Date(1536688326000)\/",
        "FileName":  "Windows10.0-KB4457138-x86.cab",
        "URL":  "http://download.windowsupdate.com/d/msdownload/update/software/secu/2018/09/windows10.0-kb4457138-x86_aa43982cc26c46180b00034886558ef09808583e.cab"
    },
    {
        "Category":  "Cumulative",
        "KBNumber":  "4457132",
        "KBTitle":  "2018-09 Cumulative Update for Windows 10 Version 1507 for x86-based Systems (KB4457132)",
        "KBUrl":  "http://support.microsoft.com/help/4457132",
        "Severity":  "Critical",
        "DatePosted":  "\/Date(1536685205000)\/",
        "DateRevised":  "\/Date(1536685205000)\/",
        "DateCreated":  "\/Date(1536688312000)\/",
        "DateLastModified":  "\/Date(1536688312000)\/",
        "FileName":  "Windows10.0-KB4457132-x86.cab",
        "URL":  "http://download.windowsupdate.com/d/msdownload/update/software/secu/2018/09/windows10.0-kb4457132-x86_cb03240f6bb445b669688aeacee6dc3c2b4d66f8.cab"
    },
    {
        "Category":  "Adobe",
        "KBNumber":  "4457146",
        "KBTitle":  "2018-09 Security Update for Adobe Flash Player for Windows 10 Version 1607 for x64-based Systems (KB4457146)",
        "KBUrl":  "http://support.microsoft.com/help/4457146",
        "Severity":  "Critical",
        "DatePosted":  "\/Date(1536685205000)\/",
        "DateRevised":  "\/Date(1536685205000)\/",
        "DateCreated":  "\/Date(1536688299000)\/",
        "DateLastModified":  "\/Date(1536688299000)\/",
        "FileName":  "Windows10.0-KB4457146-X64.cab",
        "URL":  "http://download.windowsupdate.com/d/msdownload/update/software/secu/2018/09/windows10.0-kb4457146-x64_8a4219fe58dfb1857c68c2d23092721e9bfe2f7a.cab"
    },
    {
        "Category":  "Cumulative",
        "KBNumber":  "4457131",
        "KBTitle":  "2018-09 Cumulative Update for Windows 10 Version 1607 for x86-based Systems (KB4457131)",
        "KBUrl":  "http://support.microsoft.com/help/4457131",
        "Severity":  "Critical",
        "DatePosted":  "\/Date(1536685205000)\/",
        "DateRevised":  "\/Date(1536685205000)\/",
        "DateCreated":  "\/Date(1536688305000)\/",
        "DateLastModified":  "\/Date(1536688305000)\/",
        "FileName":  "Windows10.0-KB4457131-x86.cab",
        "URL":  "http://download.windowsupdate.com/d/msdownload/update/software/secu/2018/09/windows10.0-kb4457131-x86_a6ea385df1097504a20704ae848046f73105b194.cab"
    },
    {
        "Category":  "Cumulative",
        "KBNumber":  "4457138",
        "KBTitle":  "2018-09 Cumulative Update for Windows 10 Version 1703 for x64-based Systems (KB4457138)",
        "KBUrl":  "http://support.microsoft.com/help/4457138",
        "Severity":  "Critical",
        "DatePosted":  "\/Date(1536685205000)\/",
        "DateRevised":  "\/Date(1536685205000)\/",
        "DateCreated":  "\/Date(1536688322000)\/",
        "DateLastModified":  "\/Date(1536688322000)\/",
        "FileName":  "Windows10.0-KB4457138-x64.cab",
        "URL":  "http://download.windowsupdate.com/d/msdownload/update/software/secu/2018/09/windows10.0-kb4457138-x64_99c900ebdd3cc4977747d48987c58f1c8b0f53e0.cab"
    },
    {
        "Category":  "Cumulative",
        "KBNumber":  "4457132",
        "KBTitle":  "2018-09 Cumulative Update for Windows 10 Version 1507 for x64-based Systems (KB4457132)",
        "KBUrl":  "http://support.microsoft.com/help/4457132",
        "Severity":  "Critical",
        "DatePosted":  "\/Date(1536685205000)\/",
        "DateRevised":  "\/Date(1536685205000)\/",
        "DateCreated":  "\/Date(1536688311000)\/",
        "DateLastModified":  "\/Date(1536688311000)\/",
        "FileName":  "Windows10.0-KB4457132-x64.cab",
        "URL":  "http://download.windowsupdate.com/d/msdownload/update/software/secu/2018/09/windows10.0-kb4457132-x64_200a09557cc650195c136f91a0826c293023468c.cab"
    },
    {
        "Category":  "Cumulative",
        "KBNumber":  "4457131",
        "KBTitle":  "2018-09 Cumulative Update for Windows 10 Version 1607 for x64-based Systems (KB4457131)",
        "KBUrl":  "http://support.microsoft.com/help/4457131",
        "Severity":  "Critical",
        "DatePosted":  "\/Date(1536685205000)\/",
        "DateRevised":  "\/Date(1536685205000)\/",
        "DateCreated":  "\/Date(1536688303000)\/",
        "DateLastModified":  "\/Date(1536688303000)\/",
        "FileName":  "Windows10.0-KB4457131-x64.cab",
        "URL":  "http://download.windowsupdate.com/d/msdownload/update/software/secu/2018/09/windows10.0-kb4457131-x64_786e1ea5672e25d698548a3a966f48ce16530746.cab"
    },
    {
        "Category":  "Adobe",
        "KBNumber":  "4457146",
        "KBTitle":  "2018-09 Security Update for Adobe Flash Player for Windows 10 Version 1607 for x86-based Systems (KB4457146)",
        "KBUrl":  "http://support.microsoft.com/help/4457146",
        "Severity":  "Critical",
        "DatePosted":  "\/Date(1536685205000)\/",
        "DateRevised":  "\/Date(1536685205000)\/",
        "DateCreated":  "\/Date(1536688301000)\/",
        "DateLastModified":  "\/Date(1536688301000)\/",
        "FileName":  "Windows10.0-KB4457146-X86.cab",
        "URL":  "http://download.windowsupdate.com/d/msdownload/update/software/secu/2018/09/windows10.0-kb4457146-x86_bb5fbaf945b852f288822e7a58b234b24cb409e9.cab"
    },
    {
        "Category":  "Setup",
        "KBNumber":  "4340689",
        "KBTitle":  "2018-08 Dynamic Update for Windows 10 Version 1709 for x86-based Systems (KB4340689)",
        "KBUrl":  "http://support.microsoft.com/help/4340689",
        "Severity":  "",
        "DatePosted":  "\/Date(1534266005000)\/",
        "DateRevised":  "\/Date(1534266005000)\/",
        "DateCreated":  "\/Date(1534269123000)\/",
        "DateLastModified":  "\/Date(1534269123000)\/",
        "FileName":  "Windows10.0-KB4340689-x86.cab",
        "URL":  "http://download.windowsupdate.com/c/msdownload/update/software/crup/2018/07/windows10.0-kb4340689-x86_4669786b1b09b84d84cac4b973610a9876efff17.cab"
    },
    {
        "Category":  "Setup",
        "KBNumber":  "4340689",
        "KBTitle":  "2018-08 Dynamic Update for Windows 10 Version 1709 for x64-based Systems (KB4340689)",
        "KBUrl":  "http://support.microsoft.com/help/4340689",
        "Severity":  "",
        "DatePosted":  "\/Date(1534266005000)\/",
        "DateRevised":  "\/Date(1534266005000)\/",
        "DateCreated":  "\/Date(1534269143000)\/",
        "DateLastModified":  "\/Date(1534269143000)\/",
        "FileName":  "Windows10.0-KB4340689-x64.cab",
        "URL":  "http://download.windowsupdate.com/c/msdownload/update/software/crup/2018/07/windows10.0-kb4340689-x64_fbaee9f3e3fae49d2b3abe67c2e759925eff22ce.cab"
    },
    {
        "Category":  "Setup",
        "KBNumber":  "4340921",
        "KBTitle":  "2018-07 Dynamic Update for Windows 10 Version 1803 for x64-based Systems (KB4340921)",
        "KBUrl":  "http://support.microsoft.com/help/4340921",
        "Severity":  "",
        "DatePosted":  "\/Date(1532451605000)\/",
        "DateRevised":  "\/Date(1532451605000)\/",
        "DateCreated":  "\/Date(1532453930000)\/",
        "DateLastModified":  "\/Date(1532453930000)\/",
        "FileName":  "Windows10.0-KB4340921-x64.cab",
        "URL":  "http://download.windowsupdate.com/d/msdownload/update/software/crup/2018/07/windows10.0-kb4340921-x64_ef06192a7831073b9df5b04a3e99605a07695e3e.cab"
    },
    {
        "Category":  "Setup",
        "KBNumber":  "4340921",
        "KBTitle":  "2018-07 Dynamic Update for Windows 10 Version 1803 for x86-based Systems (KB4340921)",
        "KBUrl":  "http://support.microsoft.com/help/4340921",
        "Severity":  "",
        "DatePosted":  "\/Date(1532451605000)\/",
        "DateRevised":  "\/Date(1532451605000)\/",
        "DateCreated":  "\/Date(1532453934000)\/",
        "DateLastModified":  "\/Date(1532453934000)\/",
        "FileName":  "Windows10.0-KB4340921-x86.cab",
        "URL":  "http://download.windowsupdate.com/c/msdownload/update/software/crup/2018/07/windows10.0-kb4340921-x86_7289745aceda70c293bc6859627a3195beeccfa7.cab"
    },
    {
        "Category":  "Servicing",
        "KBNumber":  "4339420",
        "KBTitle":  "2018-07 Update for Windows Server 2016 (1709) for x64-based Systems (KB4339420)",
        "KBUrl":  "http://support.microsoft.com/help/4339420",
        "Severity":  "",
        "DatePosted":  "\/Date(1531242005000)\/",
        "DateRevised":  "\/Date(1531242005000)\/",
        "DateCreated":  "\/Date(1531244945000)\/",
        "DateLastModified":  "\/Date(1531244945000)\/",
        "FileName":  "Windows10.0-KB4339420-x64.cab",
        "URL":  "http://download.windowsupdate.com/c/msdownload/update/software/crup/2018/07/windows10.0-kb4339420-x64_747902958874ba4d9cc1287e59336e7921e2f442.cab"
    },
    {
        "Category":  "Servicing",
        "KBNumber":  "4339420",
        "KBTitle":  "2018-07 Update for Windows 10 Version 1709 for x64-based Systems (KB4339420)",
        "KBUrl":  "http://support.microsoft.com/help/4339420",
        "Severity":  "",
        "DatePosted":  "\/Date(1531242005000)\/",
        "DateRevised":  "\/Date(1531242005000)\/",
        "DateCreated":  "\/Date(1531244946000)\/",
        "DateLastModified":  "\/Date(1531244946000)\/",
        "FileName":  "Windows10.0-KB4339420-x64.cab",
        "URL":  "http://download.windowsupdate.com/c/msdownload/update/software/crup/2018/07/windows10.0-kb4339420-x64_747902958874ba4d9cc1287e59336e7921e2f442.cab"
    },
    {
        "Category":  "Servicing",
        "KBNumber":  "4339420",
        "KBTitle":  "2018-07 Update for Windows 10 Version 1709 for x86-based Systems (KB4339420)",
        "KBUrl":  "http://support.microsoft.com/help/4339420",
        "Severity":  "",
        "DatePosted":  "\/Date(1531242005000)\/",
        "DateRevised":  "\/Date(1531242005000)\/",
        "DateCreated":  "\/Date(1531244981000)\/",
        "DateLastModified":  "\/Date(1531244981000)\/",
        "FileName":  "Windows10.0-KB4339420-x86.cab",
        "URL":  "http://download.windowsupdate.com/d/msdownload/update/software/crup/2018/07/windows10.0-kb4339420-x86_76e42db5c55cb8cf0509b2c8875067878d557d8c.cab"
    },
    {
        "Category":  "Component",
        "KBNumber":  "4230204",
        "KBTitle":  "2018-06 Dynamic Update for Windows 10 Version 1803 for x86-based Systems (KB4230204)",
        "KBUrl":  "http://support.microsoft.com/help/4230204",
        "Severity":  "",
        "DatePosted":  "\/Date(1530032405000)\/",
        "DateRevised":  "\/Date(1530032405000)\/",
        "DateCreated":  "\/Date(1531912363000)\/",
        "DateLastModified":  "\/Date(1531912363000)\/",
        "FileName":  "Windows10.0-KB4230204-x86.cab",
        "URL":  "http://download.windowsupdate.com/d/msdownload/update/software/crup/2018/06/windows10.0-kb4230204-x86_216741fe17e23580f02bab5dbe8d76c7f63921c2.cab"
    },
    {
        "Category":  "Component",
        "KBNumber":  "4230204",
        "KBTitle":  "2018-06 Dynamic Update for Windows 10 Version 1803 for x64-based Systems (KB4230204)",
        "KBUrl":  "http://support.microsoft.com/help/4230204",
        "Severity":  "",
        "DatePosted":  "\/Date(1530032405000)\/",
        "DateRevised":  "\/Date(1530032405000)\/",
        "DateCreated":  "\/Date(1531912352000)\/",
        "DateLastModified":  "\/Date(1531912352000)\/",
        "FileName":  "Windows10.0-KB4230204-x64.cab",
        "URL":  "http://download.windowsupdate.com/d/msdownload/update/software/crup/2018/06/windows10.0-kb4230204-x64_8e34c1dcf54ac81e3b0ce45616eae2af15b4847b.cab"
    },
    {
        "Category":  "Component",
        "KBNumber":  "4293700",
        "KBTitle":  "2018-06 Dynamic Update for Windows 10 Version 1709 for x64-based Systems (KB4293700)",
        "KBUrl":  "http://support.microsoft.com/help/4293700",
        "Severity":  "",
        "DatePosted":  "\/Date(1528822805000)\/",
        "DateRevised":  "\/Date(1528822805000)\/",
        "DateCreated":  "\/Date(1531912364000)\/",
        "DateLastModified":  "\/Date(1531912364000)\/",
        "FileName":  "Windows10.0-KB4293700-x64.cab",
        "URL":  "http://download.windowsupdate.com/c/msdownload/update/software/crup/2018/05/windows10.0-kb4293700-x64_6282fdd0bc7ad848738c71e5ab9ad2cf206989c1.cab"
    },
    {
        "Category":  "Component",
        "KBNumber":  "4293700",
        "KBTitle":  "2018-06 Dynamic Update for Windows 10 Version 1709 for x86-based Systems (KB4293700)",
        "KBUrl":  "http://support.microsoft.com/help/4293700",
        "Severity":  "",
        "DatePosted":  "\/Date(1528822805000)\/",
        "DateRevised":  "\/Date(1528822805000)\/",
        "DateCreated":  "\/Date(1531912365000)\/",
        "DateLastModified":  "\/Date(1531912365000)\/",
        "FileName":  "Windows10.0-KB4293700-x86.cab",
        "URL":  "http://download.windowsupdate.com/c/msdownload/update/software/crup/2018/05/windows10.0-kb4293700-x86_a01288d6fe051cfd2429b205fd9c8d17ddc62172.cab"
    },
    {
        "Category":  "Servicing",
        "KBNumber":  "4132649",
        "KBTitle":  "2018-05 Update for Windows 10 Version 1703 for x86-based Systems (KB4132649)",
        "KBUrl":  "http://support.microsoft.com/help/4132649",
        "Severity":  "",
        "DatePosted":  "\/Date(1526576405000)\/",
        "DateRevised":  "\/Date(1526576405000)\/",
        "DateCreated":  "\/Date(1526594532000)\/",
        "DateLastModified":  "\/Date(1526594532000)\/",
        "FileName":  "Windows10.0-KB4132649-x86.cab",
        "URL":  "http://download.windowsupdate.com/c/msdownload/update/software/crup/2018/05/windows10.0-kb4132649-x86_5b3c70ead132fc1b64520596975dd6f0b7d9252a.cab"
    },
    {
        "Category":  "Servicing",
        "KBNumber":  "4132216",
        "KBTitle":  "2018-05 Update for Windows Server 2016 (1607) for x64-based Systems (KB4132216)",
        "KBUrl":  "http://support.microsoft.com/help/4132216",
        "Severity":  "",
        "DatePosted":  "\/Date(1526576405000)\/",
        "DateRevised":  "\/Date(1526576405000)\/",
        "DateCreated":  "\/Date(1526594547000)\/",
        "DateLastModified":  "\/Date(1526594547000)\/",
        "FileName":  "Windows10.0-KB4132216-x64.cab",
        "URL":  "http://download.windowsupdate.com/c/msdownload/update/software/crup/2018/05/windows10.0-kb4132216-x64_10446dde66774e805051a36c897142d619249808.cab"
    },
    {
        "Category":  "Servicing",
        "KBNumber":  "4132649",
        "KBTitle":  "2018-05 Update for Windows 10 Version 1703 for x64-based Systems (KB4132649)",
        "KBUrl":  "http://support.microsoft.com/help/4132649",
        "Severity":  "",
        "DatePosted":  "\/Date(1526576405000)\/",
        "DateRevised":  "\/Date(1526576405000)\/",
        "DateCreated":  "\/Date(1526594537000)\/",
        "DateLastModified":  "\/Date(1526594537000)\/",
        "FileName":  "Windows10.0-KB4132649-x64.cab",
        "URL":  "http://download.windowsupdate.com/c/msdownload/update/software/crup/2018/05/windows10.0-kb4132649-x64_879b04411f1964fee490c969fc40da820a27535e.cab"
    },
    {
        "Category":  "Servicing",
        "KBNumber":  "4132216",
        "KBTitle":  "2018-05 Update for Windows 10 Version 1607 for x86-based Systems (KB4132216)",
        "KBUrl":  "http://support.microsoft.com/help/4132216",
        "Severity":  "",
        "DatePosted":  "\/Date(1526576405000)\/",
        "DateRevised":  "\/Date(1526576405000)\/",
        "DateCreated":  "\/Date(1526594533000)\/",
        "DateLastModified":  "\/Date(1526594533000)\/",
        "FileName":  "Windows10.0-KB4132216-x86.cab",
        "URL":  "http://download.windowsupdate.com/c/msdownload/update/software/crup/2018/05/windows10.0-kb4132216-x86_549edb80959d94ef158f5a7c7dfd7effaed8b169.cab"
    },
    {
        "Category":  "Servicing",
        "KBNumber":  "4132216",
        "KBTitle":  "2018-05 Update for Windows 10 Version 1607 for x64-based Systems (KB4132216)",
        "KBUrl":  "http://support.microsoft.com/help/4132216",
        "Severity":  "",
        "DatePosted":  "\/Date(1526576405000)\/",
        "DateRevised":  "\/Date(1526576405000)\/",
        "DateCreated":  "\/Date(1526594550000)\/",
        "DateLastModified":  "\/Date(1526594550000)\/",
        "FileName":  "Windows10.0-KB4132216-x64.cab",
        "URL":  "http://download.windowsupdate.com/c/msdownload/update/software/crup/2018/05/windows10.0-kb4132216-x64_10446dde66774e805051a36c897142d619249808.cab"
    },
    {
        "Category":  "Cumulative",
        "KBNumber":  "4093109",
        "KBTitle":  "2018-04 Cumulative Update for Windows 10 Version 1511 for x64-based Systems (KB4093109)",
        "KBUrl":  "http://support.microsoft.com/help/4093109",
        "Severity":  "Critical",
        "DatePosted":  "\/Date(1523379665000)\/",
        "DateRevised":  "\/Date(1523379665000)\/",
        "DateCreated":  "\/Date(1523382120000)\/",
        "DateLastModified":  "\/Date(1523382120000)\/",
        "FileName":  "Windows10.0-KB4093109-x64.cab",
        "URL":  "http://download.windowsupdate.com/d/msdownload/update/software/secu/2018/03/windows10.0-kb4093109-x64_263019e9affdd06651413f3fed25c07d498ea38d.cab"
    },
    {
        "Category":  "Cumulative",
        "KBNumber":  "4093109",
        "KBTitle":  "2018-04 Cumulative Update for Windows 10 Version 1511 for x86-based Systems (KB4093109)",
        "KBUrl":  "http://support.microsoft.com/help/4093109",
        "Severity":  "Critical",
        "DatePosted":  "\/Date(1523379665000)\/",
        "DateRevised":  "\/Date(1523379665000)\/",
        "DateCreated":  "\/Date(1523382116000)\/",
        "DateLastModified":  "\/Date(1523382116000)\/",
        "FileName":  "Windows10.0-KB4093109-x86.cab",
        "URL":  "http://download.windowsupdate.com/d/msdownload/update/software/secu/2018/03/windows10.0-kb4093109-x86_6bd17cae67d80097b55cd40b806f227db922a56c.cab"
    },
    {
        "Category":  "Servicing",
        "KBNumber":  "4093430",
        "KBTitle":  "2018-04 Update for Windows 10 Version 1507 for x64-based Systems (KB4093430)",
        "KBUrl":  "http://support.microsoft.com/help/4093430",
        "Severity":  "",
        "DatePosted":  "\/Date(1523379605000)\/",
        "DateRevised":  "\/Date(1523379605000)\/",
        "DateCreated":  "\/Date(1523382098000)\/",
        "DateLastModified":  "\/Date(1523382098000)\/",
        "FileName":  "Windows10.0-KB4093430-x64.cab",
        "URL":  "http://download.windowsupdate.com/d/msdownload/update/software/crup/2018/03/windows10.0-kb4093430-x64_753987fc0dae9cde3e0e9da204285fa797ecf828.cab"
    },
    {
        "Category":  "Servicing",
        "KBNumber":  "4093430",
        "KBTitle":  "2018-04 Update for Windows 10 Version 1507 for x86-based Systems (KB4093430)",
        "KBUrl":  "http://support.microsoft.com/help/4093430",
        "Severity":  "",
        "DatePosted":  "\/Date(1523379605000)\/",
        "DateRevised":  "\/Date(1523379605000)\/",
        "DateCreated":  "\/Date(1523382093000)\/",
        "DateLastModified":  "\/Date(1523382093000)\/",
        "FileName":  "Windows10.0-KB4093430-x86.cab",
        "URL":  "http://download.windowsupdate.com/d/msdownload/update/software/crup/2018/03/windows10.0-kb4093430-x86_947d8cbfeafa3033c7bc22f73b8a026122bca05a.cab"
    },
    {
        "Category":  "Adobe",
        "KBNumber":  "4093110",
        "KBTitle":  "2018-04 Security Update for Adobe Flash Player for Windows 10 Version 1511 for x86-based Systems (KB4093110)",
        "KBUrl":  "http://support.microsoft.com/help/4093110",
        "Severity":  "Critical",
        "DatePosted":  "\/Date(1523379605000)\/",
        "DateRevised":  "\/Date(1523379605000)\/",
        "DateCreated":  "\/Date(1523382092000)\/",
        "DateLastModified":  "\/Date(1523382092000)\/",
        "FileName":  "Windows10.0-KB4093110-X86.cab",
        "URL":  "http://download.windowsupdate.com/d/msdownload/update/software/secu/2018/04/windows10.0-kb4093110-x86_0d8fd79563fe7b7dd00dcf99e2001e9ef391b207.cab"
    },
    {
        "Category":  "Adobe",
        "KBNumber":  "4093110",
        "KBTitle":  "2018-04 Security Update for Adobe Flash Player for Windows 10 Version 1511 for x64-based Systems (KB4093110)",
        "KBUrl":  "http://support.microsoft.com/help/4093110",
        "Severity":  "Critical",
        "DatePosted":  "\/Date(1523379605000)\/",
        "DateRevised":  "\/Date(1523379605000)\/",
        "DateCreated":  "\/Date(1523382093000)\/",
        "DateLastModified":  "\/Date(1523382093000)\/",
        "FileName":  "Windows10.0-KB4093110-X64.cab",
        "URL":  "http://download.windowsupdate.com/d/msdownload/update/software/secu/2018/04/windows10.0-kb4093110-x64_253a81268d68278e5701dd6c3cc3aec6bd338b34.cab"
    },
    {
        "Category":  "Component",
        "KBNumber":  "4094276",
        "KBTitle":  "2018-03 Dynamic Update for Windows 10 Version 1709 for x86-based Systems (KB4094276)",
        "KBUrl":  "http://support.microsoft.com/help/4094276",
        "Severity":  "",
        "DatePosted":  "\/Date(1521738005000)\/",
        "DateRevised":  "\/Date(1521738005000)\/",
        "DateCreated":  "\/Date(1531912333000)\/",
        "DateLastModified":  "\/Date(1531912333000)\/",
        "FileName":  "Windows10.0-KB4094276-x86.cab",
        "URL":  "http://download.windowsupdate.com/c/msdownload/update/software/crup/2018/03/windows10.0-kb4094276-x86_a73a857c0d062fb8ec6419db9445dfa6e64b01d4.cab"
    },
    {
        "Category":  "Component",
        "KBNumber":  "4094276",
        "KBTitle":  "2018-03 Dynamic Update for Windows 10 Version 1709 for x64-based Systems (KB4094276)",
        "KBUrl":  "http://support.microsoft.com/help/4094276",
        "Severity":  "",
        "DatePosted":  "\/Date(1521738005000)\/",
        "DateRevised":  "\/Date(1521738005000)\/",
        "DateCreated":  "\/Date(1531912331000)\/",
        "DateLastModified":  "\/Date(1531912331000)\/",
        "FileName":  "Windows10.0-KB4094276-x64.cab",
        "URL":  "http://download.windowsupdate.com/c/msdownload/update/software/crup/2018/03/windows10.0-kb4094276-x64_db7ab37d8a2baf82964a074bc2d5676bc6fc8d2f.cab"
    },
    {
        "Category":  "Component",
        "KBNumber":  "4078408",
        "KBTitle":  "2018-02 Dynamic Update for Windows 10 Version 1709 for x64-based Systems (KB4078408)",
        "KBUrl":  "http://support.microsoft.com/help/4078408",
        "Severity":  "",
        "DatePosted":  "\/Date(1518544805000)\/",
        "DateRevised":  "\/Date(1518544805000)\/",
        "DateCreated":  "\/Date(1531912326000)\/",
        "DateLastModified":  "\/Date(1531912326000)\/",
        "FileName":  "Windows10.0-KB4078408-x64.cab",
        "URL":  "http://download.windowsupdate.com/c/msdownload/update/software/crup/2018/02/windows10.0-kb4078408-x64_bea4bb343fe962ffb5ef036e01f5c07156347215.cab"
    },
    {
        "Category":  "Setup",
        "KBNumber":  "4077962",
        "KBTitle":  "2018-02 Dynamic Update for Windows 10 Version 1703 for x86-based Systems (KB4077962)",
        "KBUrl":  "http://support.microsoft.com/help/4077962",
        "Severity":  "",
        "DatePosted":  "\/Date(1518544805000)\/",
        "DateRevised":  "\/Date(1518544805000)\/",
        "DateCreated":  "\/Date(1531912346000)\/",
        "DateLastModified":  "\/Date(1531912346000)\/",
        "FileName":  "Windows10.0-KB4077962-x86.cab",
        "URL":  "http://download.windowsupdate.com/c/msdownload/update/software/crup/2018/02/windows10.0-kb4077962-x86_5b9ae885568420d20885cba2c519a54cea3dbcdf.cab"
    },
    {
        "Category":  "Component",
        "KBNumber":  "4078408",
        "KBTitle":  "2018-02 Dynamic Update for Windows 10 Version 1709 for x86-based Systems (KB4078408)",
        "KBUrl":  "http://support.microsoft.com/help/4078408",
        "Severity":  "",
        "DatePosted":  "\/Date(1518544805000)\/",
        "DateRevised":  "\/Date(1518544805000)\/",
        "DateCreated":  "\/Date(1531912335000)\/",
        "DateLastModified":  "\/Date(1531912335000)\/",
        "FileName":  "Windows10.0-KB4078408-x86.cab",
        "URL":  "http://download.windowsupdate.com/c/msdownload/update/software/crup/2018/02/windows10.0-kb4078408-x86_9da56a735a2a7419cd7738d9fe959c68b98b961a.cab"
    },
    {
        "Category":  "Setup",
        "KBNumber":  "4077962",
        "KBTitle":  "2018-02 Dynamic Update for Windows 10 Version 1703 for x64-based Systems (KB4077962)",
        "KBUrl":  "http://support.microsoft.com/help/4077962",
        "Severity":  "",
        "DatePosted":  "\/Date(1518544805000)\/",
        "DateRevised":  "\/Date(1518544805000)\/",
        "DateCreated":  "\/Date(1531912349000)\/",
        "DateLastModified":  "\/Date(1531912349000)\/",
        "FileName":  "Windows10.0-KB4077962-x64.cab",
        "URL":  "http://download.windowsupdate.com/c/msdownload/update/software/crup/2018/02/windows10.0-kb4077962-x64_b4a426125ad0dab1c9edd7003373afc86f8426a1.cab"
    },
    {
        "Category":  "Component",
        "KBNumber":  "4055994",
        "KBTitle":  "2017-12 Dynamic Update for Windows 10 Version 1709 for x64-based Systems (KB4055994)",
        "KBUrl":  "http://support.microsoft.com/help/4055994",
        "Severity":  "",
        "DatePosted":  "\/Date(1513101605000)\/",
        "DateRevised":  "\/Date(1513101605000)\/",
        "DateCreated":  "\/Date(1531912315000)\/",
        "DateLastModified":  "\/Date(1531912315000)\/",
        "FileName":  "Windows10.0-KB4055994-x64.cab",
        "URL":  "http://download.windowsupdate.com/c/msdownload/update/software/crup/2017/12/windows10.0-kb4055994-x64_6b4567ad4f0c9cb98bef54a6d06d4561e17292df.cab"
    },
    {
        "Category":  "Component",
        "KBNumber":  "4055994",
        "KBTitle":  "2017-12 Dynamic Update for Windows 10 Version 1709 for x86-based Systems (KB4055994)",
        "KBUrl":  "http://support.microsoft.com/help/4055994",
        "Severity":  "",
        "DatePosted":  "\/Date(1513101605000)\/",
        "DateRevised":  "\/Date(1513101605000)\/",
        "DateCreated":  "\/Date(1531912314000)\/",
        "DateLastModified":  "\/Date(1531912314000)\/",
        "FileName":  "Windows10.0-KB4055994-x86.cab",
        "URL":  "http://download.windowsupdate.com/c/msdownload/update/software/crup/2017/12/windows10.0-kb4055994-x86_9cee0fecfae7635eb962fa7bcd3fba4d7c6e9e6c.cab"
    },
    {
        "Category":  "Component",
        "KBNumber":  "4055237",
        "KBTitle":  "2017-11 Dynamic Update for Windows 10 Version 1709 for x86-based Systems (KB4055237)",
        "KBUrl":  "http://support.microsoft.com/help/4055237",
        "Severity":  "",
        "DatePosted":  "\/Date(1512064805000)\/",
        "DateRevised":  "\/Date(1512064805000)\/",
        "DateCreated":  "\/Date(1531912319000)\/",
        "DateLastModified":  "\/Date(1531912319000)\/",
        "FileName":  "Windows10.0-KB4055237-x86.cab",
        "URL":  "http://download.windowsupdate.com/c/msdownload/update/software/crup/2017/11/windows10.0-kb4055237-x86_824425013ac510a6aebd39459c52c927d14c2e0c.cab"
    },
    {
        "Category":  "Component",
        "KBNumber":  "4055237",
        "KBTitle":  "2017-11 Dynamic Update for Windows 10 Version 1709 for x64-based Systems (KB4055237)",
        "KBUrl":  "http://support.microsoft.com/help/4055237",
        "Severity":  "",
        "DatePosted":  "\/Date(1512064805000)\/",
        "DateRevised":  "\/Date(1512064805000)\/",
        "DateCreated":  "\/Date(1531912310000)\/",
        "DateLastModified":  "\/Date(1531912310000)\/",
        "FileName":  "Windows10.0-KB4055237-x64.cab",
        "URL":  "http://download.windowsupdate.com/d/msdownload/update/software/crup/2017/11/windows10.0-kb4055237-x64_38258288cae1f63ed0a238752b8270960f4dc48c.cab"
    },
    {
        "Category":  "Setup",
        "KBNumber":  "4039556",
        "KBTitle":  "2017-09 Dynamic Update for Windows 10 Version 1607 for x64-based Systems (KB4039556)",
        "KBUrl":  "http://support.microsoft.com/help/4039556",
        "Severity":  "",
        "DatePosted":  "\/Date(1505235603000)\/",
        "DateRevised":  "\/Date(1505235603000)\/",
        "DateCreated":  "\/Date(1531912317000)\/",
        "DateLastModified":  "\/Date(1531912317000)\/",
        "FileName":  "Windows10.0-KB4039556-x64.cab",
        "URL":  "http://download.windowsupdate.com/d/msdownload/update/software/crup/2017/08/windows10.0-kb4039556-x64_c254664797da48390e795776340844c76343876c.cab"
    },
    {
        "Category":  "Setup",
        "KBNumber":  "4039556",
        "KBTitle":  "2017-09 Dynamic Update for Windows 10 Version 1607 for x86-based Systems (KB4039556)",
        "KBUrl":  "http://support.microsoft.com/help/4039556",
        "Severity":  "",
        "DatePosted":  "\/Date(1505235603000)\/",
        "DateRevised":  "\/Date(1505235603000)\/",
        "DateCreated":  "\/Date(1531912312000)\/",
        "DateLastModified":  "\/Date(1531912312000)\/",
        "FileName":  "Windows10.0-KB4039556-x86.cab",
        "URL":  "http://download.windowsupdate.com/d/msdownload/update/software/crup/2017/08/windows10.0-kb4039556-x86_fb4d1d70abfed98e7d432cc2692f8693bfd18925.cab"
    },
    {
        "Category":  "Servicing",
        "KBNumber":  "4035632",
        "KBTitle":  "2017-08 Update for Windows 10 Version 1511 for x64-based Systems (KB4035632)",
        "KBUrl":  "http://support.microsoft.com/help/4035632",
        "Severity":  "",
        "DatePosted":  "\/Date(1502211603000)\/",
        "DateRevised":  "\/Date(1502211603000)\/",
        "DateCreated":  "\/Date(1502216646000)\/",
        "DateLastModified":  "\/Date(1502216646000)\/",
        "FileName":  "Windows10.0-KB4035632-x64.cab",
        "URL":  "http://wsus.ds.download.windowsupdate.com/d/msdownload/update/software/crup/2017/08/windows10.0-kb4035632-x64_3258f1347a821d7afac57b58ec87cb951dcdd671.cab"
    },
    {
        "Category":  "Servicing",
        "KBNumber":  "4035632",
        "KBTitle":  "2017-08 Update for Windows 10 Version 1511 for x86-based Systems (KB4035632)",
        "KBUrl":  "http://support.microsoft.com/help/4035632",
        "Severity":  "",
        "DatePosted":  "\/Date(1502211603000)\/",
        "DateRevised":  "\/Date(1502211603000)\/",
        "DateCreated":  "\/Date(1502216647000)\/",
        "DateLastModified":  "\/Date(1502216647000)\/",
        "FileName":  "Windows10.0-KB4035632-x86.cab",
        "URL":  "http://wsus.ds.download.windowsupdate.com/d/msdownload/update/software/crup/2017/08/windows10.0-kb4035632-x86_93b0ebe4cd09b9f4b40f6ec8070300cbe34d57d9.cab"
    },
    {
        "Category":  "Component",
        "KBNumber":  "4021572",
        "KBTitle":  "2017-05 Dynamic Update for Windows 10 Version 1703 for x86-based Systems (KB4021572)",
        "KBUrl":  "http://support.microsoft.com/help/4021572",
        "Severity":  "",
        "DatePosted":  "\/Date(1495558803000)\/",
        "DateRevised":  "\/Date(1495558803000)\/",
        "DateCreated":  "\/Date(1531912321000)\/",
        "DateLastModified":  "\/Date(1531912321000)\/",
        "FileName":  "Windows10.0-KB4021572-x86.cab",
        "URL":  "http://download.windowsupdate.com/c/msdownload/update/software/crup/2017/05/windows10.0-kb4021572-x86_ddb5e001e92f89181c6fd2ca164419ae614f58eb.cab"
    },
    {
        "Category":  "Component",
        "KBNumber":  "4021572",
        "KBTitle":  "2017-05 Dynamic Update for Windows 10 Version 1703 for x64-based Systems (KB4021572)",
        "KBUrl":  "http://support.microsoft.com/help/4021572",
        "Severity":  "",
        "DatePosted":  "\/Date(1495558803000)\/",
        "DateRevised":  "\/Date(1495558803000)\/",
        "DateCreated":  "\/Date(1531912316000)\/",
        "DateLastModified":  "\/Date(1531912316000)\/",
        "FileName":  "Windows10.0-KB4021572-x64.cab",
        "URL":  "http://download.windowsupdate.com/c/msdownload/update/software/crup/2017/05/windows10.0-kb4021572-x64_98c7220bba2cca05caab99a257190b61785844a0.cab"
    },
    {
        "Category":  "Component",
        "KBNumber":  "4013419",
        "KBTitle":  "2017-03 Dynamic Update for Windows 10 Version 1607 for x86-based Systems (KB4013419)",
        "KBUrl":  "http://support.microsoft.com/kb/4013419",
        "Severity":  "",
        "DatePosted":  "\/Date(1489510803000)\/",
        "DateRevised":  "\/Date(1489510803000)\/",
        "DateCreated":  "\/Date(1531912309000)\/",
        "DateLastModified":  "\/Date(1531912309000)\/",
        "FileName":  "Windows10.0-KB4013419-x86.cab",
        "URL":  "http://download.windowsupdate.com/d/msdownload/update/software/crup/2017/03/windows10.0-kb4013419-x86_2c073c2ac70ff1bdf2adba996c19d66b6b913e7c.cab"
    },
    {
        "Category":  "Component",
        "KBNumber":  "4013419",
        "KBTitle":  "2017-03 Dynamic Update for Windows 10 Version 1607 for x64-based Systems (KB4013419)",
        "KBUrl":  "http://support.microsoft.com/kb/4013419",
        "Severity":  "",
        "DatePosted":  "\/Date(1489510803000)\/",
        "DateRevised":  "\/Date(1489510803000)\/",
        "DateCreated":  "\/Date(1531912316000)\/",
        "DateLastModified":  "\/Date(1531912316000)\/",
        "FileName":  "Windows10.0-KB4013419-x64.cab",
        "URL":  "http://download.windowsupdate.com/c/msdownload/update/software/crup/2017/03/windows10.0-kb4013419-x64_c7ef71ef428fe3d2e105493b8646b8870913f250.cab"
    },
    {
        "Category":  "Component",
        "KBNumber":  "3194623",
        "KBTitle":  "2016-12 Dynamic Update for Windows 10 Version 1607 for x64-based Systems (KB3194623)",
        "KBUrl":  "http://support.microsoft.com/kb/3194623",
        "Severity":  "",
        "DatePosted":  "\/Date(1482760800000)\/",
        "DateRevised":  "\/Date(1482760800000)\/",
        "DateCreated":  "\/Date(1531912319000)\/",
        "DateLastModified":  "\/Date(1531912319000)\/",
        "FileName":  "Windows10.0-KB3194623-x64.cab",
        "URL":  "http://download.windowsupdate.com/d/msdownload/update/software/crup/2016/09/windows10.0-kb3194623-x64_24ed2b997a5b908f65b4b95bd3e29f371cfae321.cab"
    },
    {
        "Category":  "Component",
        "KBNumber":  "3197099",
        "KBTitle":  "2016-10 Dynamic Update for Windows 10 Version 1607 for x64-based Systems (KB3197099)",
        "KBUrl":  "http://support.microsoft.com/kb/3197099",
        "Severity":  "",
        "DatePosted":  "\/Date(1476205200000)\/",
        "DateRevised":  "\/Date(1476205200000)\/",
        "DateCreated":  "\/Date(1531912322000)\/",
        "DateLastModified":  "\/Date(1531912322000)\/",
        "FileName":  "Windows10.0-KB3197099-x64.cab",
        "URL":  "http://download.windowsupdate.com/c/msdownload/update/software/crup/2016/10/windows10.0-kb3197099-x64_6302b5ce441ff0e40b041970daca0597d7af848d.cab"
    },
    {
        "Category":  "Component",
        "KBNumber":  "3197099",
        "KBTitle":  "2016-10 Dynamic Update for Windows 10 Version 1607 for x86-based Systems (KB3197099)",
        "KBUrl":  "http://support.microsoft.com/kb/3197099",
        "Severity":  "",
        "DatePosted":  "\/Date(1476205200000)\/",
        "DateRevised":  "\/Date(1476205200000)\/",
        "DateCreated":  "\/Date(1531912311000)\/",
        "DateLastModified":  "\/Date(1531912311000)\/",
        "FileName":  "Windows10.0-KB3197099-x86.cab",
        "URL":  "http://download.windowsupdate.com/c/msdownload/update/software/crup/2016/10/windows10.0-kb3197099-x86_0b211b88968b5c0e99c80dba685fa4d293927681.cab"
    },
    {
        "Category":  "Component",
        "KBNumber":  "3176937",
        "KBTitle":  "2016-08 Dynamic Update for Windows 10 Version 1607 for x86-based Systems (KB3176937)",
        "KBUrl":  "http://support.microsoft.com/kb/3176937",
        "Severity":  "",
        "DatePosted":  "\/Date(1471971600000)\/",
        "DateRevised":  "\/Date(1471971600000)\/",
        "DateCreated":  "\/Date(1531912322000)\/",
        "DateLastModified":  "\/Date(1531912322000)\/",
        "FileName":  "Windows10.0-KB3176937-x86.cab",
        "URL":  "http://download.windowsupdate.com/c/msdownload/update/software/crup/2016/08/windows10.0-kb3176937-x86_8d7a0adffe677d947e6056ed3e8cda31a6d69b0c.cab"
    },
    {
        "Category":  "Component",
        "KBNumber":  "3176937",
        "KBTitle":  "2016-08 Dynamic Update for Windows 10 Version 1607 for x64-based Systems (KB3176937)",
        "KBUrl":  "http://support.microsoft.com/kb/3176937",
        "Severity":  "",
        "DatePosted":  "\/Date(1471971600000)\/",
        "DateRevised":  "\/Date(1471971600000)\/",
        "DateCreated":  "\/Date(1531912323000)\/",
        "DateLastModified":  "\/Date(1531912323000)\/",
        "FileName":  "Windows10.0-KB3176937-x64.cab",
        "URL":  "http://download.windowsupdate.com/c/msdownload/update/software/crup/2016/08/windows10.0-kb3176937-x64_a701c9df20cd812955e99a52200dd9012aa5202a.cab"
    }
]
